oauth_pyzure/__init__.py
oauth_pyzure/oauth.py
oauth_pyzure-0.1.5.dist-info/LICENSE
oauth_pyzure-0.1.5.dist-info/METADATA
oauth_pyzure-0.1.5.dist-info/WHEEL
oauth_pyzure-0.1.5.dist-info/top_level.txt
oauth_pyzure-0.1.5.dist-info/RECORD
