Metadata-Version: 2.1
Name: oauth-pyzure
Version: 0.1.5
Summary: OAuth Pyzure: OAuth for Python with Azure
Home-page: https://github.com/agu3rra/oauth-pyzure
Author: Andre Guerra
Author-email: agu3rra@gmail.com
License: MIT
Keywords: api oauth authorization azure client credentials flow
Platform: UNKNOWN
Requires-Dist: requests (==2.25.1)
Requires-Dist: cryptography (==3.4.7)
Requires-Dist: pyjwt (==2.0.1)
